LICENSE
MANIFEST.in
README.md
setup.py
yeastvision/__init__.py
yeastvision/__main__.py
yeastvision/install.py
yeastvision/utils.py
yeastvision.egg-info/PKG-INFO
yeastvision.egg-info/SOURCES.txt
yeastvision.egg-info/dependency_links.txt
yeastvision.egg-info/entry_points.txt
yeastvision.egg-info/requires.txt
yeastvision.egg-info/top_level.txt
yeastvision/data/__init__.py
yeastvision/data/ims.py
yeastvision/data/utils.py
yeastvision/disk/__init__.py
yeastvision/disk/io.py
yeastvision/disk/reader.py
yeastvision/docs/__init__.py
yeastvision/docs/figs/__init__.py
yeastvision/flou/__init__.py
yeastvision/flou/blob_detect.py
yeastvision/flou/utils.py
yeastvision/ims/__init__.py
yeastvision/ims/im_funcs.py
yeastvision/ims/interpolate.py
yeastvision/ims/rife_model/IFNet.py
yeastvision/ims/rife_model/IFNet_2R.py
yeastvision/ims/rife_model/IFNet_m.py
yeastvision/ims/rife_model/RIFE.py
yeastvision/ims/rife_model/__init__.py
yeastvision/ims/rife_model/laplacian.py
yeastvision/ims/rife_model/loss.py
yeastvision/ims/rife_model/refine.py
yeastvision/ims/rife_model/refine_2R.py
yeastvision/ims/rife_model/warplayer.py
yeastvision/ims/rife_model/pytorch_msssim/__init__.py
yeastvision/models/__init__.py
yeastvision/models/cp.py
yeastvision/models/model.py
yeastvision/models/model_types.json
yeastvision/models/utils.py
yeastvision/models/budSeg/__init__.py
yeastvision/models/budSeg/model.py
yeastvision/models/flouSeg/__init__.py
yeastvision/models/flouSeg/model.py
yeastvision/models/matSeg/__init__.py
yeastvision/models/matSeg/model.py
yeastvision/models/proSeg/__init__.py
yeastvision/models/proSeg/model.py
yeastvision/models/spoSeg/__init__.py
yeastvision/models/spoSeg/model.py
yeastvision/parts/__init__.py
yeastvision/parts/canvas.py
yeastvision/parts/dialogs.py
yeastvision/parts/fiest_full_lifecycle_wizard.py
yeastvision/parts/fiest_wizard.py
yeastvision/parts/guiparts.py
yeastvision/parts/menu.py
yeastvision/parts/utils.py
yeastvision/parts/wizard_utils.py
yeastvision/parts/workers.py
yeastvision/plot/__init__.py
yeastvision/plot/cell_table.py
yeastvision/plot/plot.py
yeastvision/plot/types.py
yeastvision/plot/utils.py
yeastvision/track/__init__.py
yeastvision/track/cell.py
