Metadata-Version: 2.1
Name: yeastvision
Version: 0.1.58
Summary: Deep learning-enabled image analysis of the full yeast life cycle
Home-page: https://github.com/berkyalcinkaya/yeastvision
Author: Berk Yalcinkaya
Author-email: berkyalcinkaya55@gmail.com
License: BSD
Classifier: Programming Language :: Python :: 3.10
Classifier: License :: OSI Approved :: BSD License
Classifier: Operating System :: OS Independent
License-File: LICENSE
Requires-Dist: numpy==1.24
Requires-Dist: cellpose==2.1.0
Requires-Dist: charset-normalizer==3.3.2
Requires-Dist: matplotlib
Requires-Dist: munkres
Requires-Dist: opencv_python_headless
Requires-Dist: pandas==1.5.0
Requires-Dist: patchify==0.2.3
Requires-Dist: PyQt5==5.15.10
Requires-Dist: pyqtgraph==0.13.0
Requires-Dist: scikit_image
Requires-Dist: scikit_learn
Requires-Dist: scipy
Requires-Dist: torch==1.12.0
Requires-Dist: tqdm
Requires-Dist: trackpy
Requires-Dist: torchvision==0.13.1
Requires-Dist: chardet==5.2.0
Requires-Dist: memory-profiler
Requires-Dist: QSwitchControl
